snapgene_utils/__init__.py
snapgene_utils/snapgene_reader.py
snapgene_utils-0.7.0.dist-info/LICENCE.txt
snapgene_utils-0.7.0.dist-info/METADATA
snapgene_utils-0.7.0.dist-info/WHEEL
snapgene_utils-0.7.0.dist-info/top_level.txt
snapgene_utils-0.7.0.dist-info/RECORD
