Metadata-Version: 2.1
Name: snapgene-utils
Version: 0.7.0
Summary: Convert Snapgene *.dna files dict/json/biopython.
Author: poeticpete
Maintainer: petertao
License: MIT
Keywords: DNA sequence design format converter
License-File: LICENCE.txt
Requires-Dist: biopython
Requires-Dist: xmltodict
Requires-Dist: html2text
